Calculator/__init__.py
Calculator/mul/__init__.py
Calculator/sub/__init__.py
calsi-0.0.2.dist-info/LICENSE
calsi-0.0.2.dist-info/METADATA
calsi-0.0.2.dist-info/WHEEL
calsi-0.0.2.dist-info/top_level.txt
calsi-0.0.2.dist-info/RECORD
