Metadata-Version: 2.1
Name: calsi
Version: 0.0.2
Summary: To perform calculator actions
Home-page: UNKNOWN
Author: Pavan
License: UNKNOWN
Platform: UNKNOWN
Classifier: License :: OSI Approved :: MIT License
Classifier: Programming Language :: Python :: 3
Classifier: Operating System :: OS Independent
Requires-Python: >=3.9.5
License-File: LICENSE
